getdevinfo/__init__.py
getdevinfo/__main__.py
getdevinfo/cygwin.py
getdevinfo/getdevinfo.py
getdevinfo/linux.py
getdevinfo/macos.py
getdevinfo/tests.py
getdevinfo/tests/__init__.py
getdevinfo/tests/getdevinfo_test_data.py
getdevinfo/tests/getdevinfo_test_functions.py
getdevinfo/tests/getdevinfo_tests_cygwin.py
getdevinfo/tests/getdevinfo_tests_linux.py
getdevinfo/tests/getdevinfo_tests_macos.py
getdevinfo-2.0.0.dist-info/LICENSE
getdevinfo-2.0.0.dist-info/METADATA
getdevinfo-2.0.0.dist-info/WHEEL
getdevinfo-2.0.0.dist-info/top_level.txt
getdevinfo-2.0.0.dist-info/RECORD
